lbcapi3/__init__.py
lbcapi3/api.py
lbcapi3-1.0.0.dist-info/METADATA
lbcapi3-1.0.0.dist-info/WHEEL
lbcapi3-1.0.0.dist-info/top_level.txt
lbcapi3-1.0.0.dist-info/RECORD
